core/__init__.py
core/cli.py
core/rules.xml
core/scanner.py
core/settings.py
core/utils.py
nodejsscan-3.4.dist-info/METADATA
nodejsscan-3.4.dist-info/RECORD
nodejsscan-3.4.dist-info/WHEEL
nodejsscan-3.4.dist-info/entry_points.txt
nodejsscan-3.4.dist-info/top_level.txt
