Metadata-Version: 2.1
Name: nodejsscan
Version: 3.4
Summary: Static security code scanner (SAST) for Node.js applications
Home-page: http://pypi.python.org/pypi/nodejsscan/
Author: Ajin Abraham
Author-email: ajin25@gmail.com
License: GPL v3
Platform: UNKNOWN
Classifier: Development Status :: 5 - Production/Stable
Classifier: Intended Audience :: Developers
Classifier: License :: OSI Approved :: GNU General Public License v3 (GPLv3)
Classifier: Programming Language :: Python :: 3
Requires-Dist: jsbeautifier (==1.7.5)
Requires-Dist: defusedxml (==0.5.0)
